flag_engine/__init__.py
flag_engine/engine.py
flag_engine/py.typed
flag_engine/context/__init__.py
flag_engine/context/mappers.py
flag_engine/context/types.py
flag_engine/result/__init__.py
flag_engine/result/types.py
flag_engine/segments/__init__.py
flag_engine/segments/constants.py
flag_engine/segments/evaluator.py
flag_engine/segments/types.py
flag_engine/segments/utils.py
flag_engine/utils/__init__.py
flag_engine/utils/hashing.py
flag_engine/utils/semver.py
flag_engine/utils/types.py
flag_engine/utils/json/__init__.py
flag_engine/utils/json/encoders.py
flagsmith_flag_engine-10.0.0.dist-info/licenses/LICENSE.txt
flagsmith_flag_engine-10.0.0.dist-info/METADATA
flagsmith_flag_engine-10.0.0.dist-info/WHEEL
flagsmith_flag_engine-10.0.0.dist-info/top_level.txt
flagsmith_flag_engine-10.0.0.dist-info/RECORD
