Metadata-Version: 2.4
Name: flagsmith-flag-engine
Version: 10.0.0
Summary: Flag engine for the Flagsmith API.
Home-page: https://github.com/Flagsmith/flagsmith-engine
Author: Flagsmith
Author-email: support@flagsmith.com
License: BSD3
Classifier: License :: OSI Approved :: BSD License
Classifier: Programming Language :: Python :: 3
Classifier: Programming Language :: Python :: 3.9
Classifier: Programming Language :: Python :: 3.10
Classifier: Programming Language :: Python :: 3.11
Classifier: Programming Language :: Python :: 3.12
Classifier: Programming Language :: Python :: 3.13
License-File: LICENSE.txt
Requires-Dist: jsonpath-rfc9535<1,>=0.1.5
Requires-Dist: semver<4,>=3.0.4
Requires-Dist: typing-extensions<5,>=4.14.1
Dynamic: author
Dynamic: author-email
Dynamic: classifier
Dynamic: description
Dynamic: description-content-type
Dynamic: home-page
Dynamic: license
Dynamic: license-file
Dynamic: requires-dist
Dynamic: summary
